envmanager/__init__.py
envmanager/core.py
envmanager/decorators/__init__.py
envmanager/decorators/envloader.py
envmanager/exceptions/__init__.py
envmanager/exceptions/main.py
envmanager/utils/__init__.py
envmanager/utils/helpers.py
envmanager/utils/resources.py
envmanager-8.1.8.dist-info/LICENSE.txt
envmanager-8.1.8.dist-info/METADATA
envmanager-8.1.8.dist-info/WHEEL
envmanager-8.1.8.dist-info/top_level.txt
envmanager-8.1.8.dist-info/RECORD
