Metadata-Version: 2.1
Name: envmanager
Version: 8.1.8
Summary: Validated environment variable management
Home-page: https://github.com/arianseyedi/python-envmanager
Author: Arian Seyedi @Bytect
Author-email: bytectgroup@gmail.com
License: MIT
Download-URL: https://github.com/arianseyedi/python-envmanager/archive/v8.1.8.tar.gz
Keywords: environment,variables,parsing,config,configuration,envvars
Platform: UNKNOWN
Classifier: Development Status :: 5 - Production/Stable
Classifier: Intended Audience :: Developers
Classifier: Topic :: Software Development :: Build Tools
Classifier: License :: OSI Approved :: MIT License
Classifier: Programming Language :: Python :: 3
Classifier: Programming Language :: Python :: 3.4
Classifier: Programming Language :: Python :: 3.5
Classifier: Programming Language :: Python :: 3.6
Classifier: Programming Language :: Python :: 3.7
Classifier: Programming Language :: Python :: 3.8
Requires-Dist: marshmallow
